CHANGES.txt
LICENSE.txt
README.txt
setup.cfg
setup.py
docs/Makefile
docs/conf.py
docs/index.rst
repoze/__init__.py
repoze.who.deprecatedplugins.egg-info/PKG-INFO
repoze.who.deprecatedplugins.egg-info/SOURCES.txt
repoze.who.deprecatedplugins.egg-info/dependency_links.txt
repoze.who.deprecatedplugins.egg-info/namespace_packages.txt
repoze.who.deprecatedplugins.egg-info/not-zip-safe
repoze.who.deprecatedplugins.egg-info/requires.txt
repoze.who.deprecatedplugins.egg-info/top_level.txt
repoze/who/__init__.py
repoze/who/plugins/__init__.py
repoze/who/plugins/cookie.py
repoze/who/plugins/form.py
repoze/who/plugins/tests/__init__.py
repoze/who/plugins/tests/test_cookie.py
repoze/who/plugins/tests/test_form.py
repoze/who/plugins/tests/fixtures/form.html